plot/__init__.py
plot/main.py
plot/run.py
plot/work.py
plot/workflow.py
plot/apps/__init__.py
plot/apps/draw.py
plot/apps/_tk/__init__.py
plot/apps/_tk/append_addon.py
plot/apps/bar/__init__.py
plot/apps/bar/bar_generator.py
plot/apps/bar/draw_horizontal_bars.py
plot/apps/bar/draw_one_bar_series.py
plot/apps/bar/draw_vertical_bars.py
plot/apps/bar/main.py
plot/apps/line/__init__.py
plot/apps/line/draw_one_line.py
plot/apps/line/main.py
plot/apps/matrix/__init__.py
plot/apps/matrix/draw_matrix.py
plot/apps/matrix/main.py
plot/apps/matrix/set_aspect_ratio.py
plot/apps/matrix/set_axis_extent.py
plot/apps/matrix/set_x_extent.py
plot/apps/matrix/set_y_extent.py
plot/apps/region/__init__.py
plot/apps/region/draw_one_region.py
plot/apps/region/main.py
plot/apps/rule/__init__.py
plot/apps/rule/draw_horizontal_rule.py
plot/apps/rule/draw_vertical_rule.py
plot/apps/rule/main.py
plot/apps/scatter/__init__.py
plot/apps/scatter/draw_one.py
plot/apps/scatter/main.py
plot/apps/span/__init__.py
plot/apps/span/draw_horizontal_span.py
plot/apps/span/draw_vertical_span.py
plot/apps/span/main.py
plot/canvas/__init__.py
plot/canvas/create.py
plot/canvas/subplots/__init__.py
plot/canvas/subplots/create.py
plot/canvas/subplots/global_axis.py
plot/canvas/subplots/subplot_spacing.py
plot/canvas/subplots/twin_axis.py
plot/deps/__init__.py
plot/deps/_umsgpack.py
plot/finetune/__init__.py
plot/finetune/finetune.py
plot/finetune/global_axis/__init__.py
plot/finetune/global_axis/add_axis_labels.py
plot/finetune/global_axis/add_figure_title.py
plot/finetune/global_axis/add_figure_title_box.py
plot/finetune/global_axis/add_text.py
plot/finetune/global_axis/main.py
plot/finetune/global_axis/set_figure_title_anchor.py
plot/finetune/local_axis/__init__.py
plot/finetune/local_axis/add_color_bar.py
plot/finetune/local_axis/add_grid_lines.py
plot/finetune/local_axis/add_local_axis_labels.py
plot/finetune/local_axis/finetune_legend.py
plot/finetune/local_axis/hide_axis_tick_labels.py
plot-0.6.5.dist-info/LICENSE.md
plot-0.6.5.dist-info/METADATA
plot-0.6.5.dist-info/WHEEL
plot-0.6.5.dist-info/entry_points.txt
plot-0.6.5.dist-info/top_level.txt
plot-0.6.5.dist-info/RECORD
