Metadata-Version: 2.1
Name: plot
Version: 0.6.5
Summary: A matplotlib frontend executable using JSON file as user input
Home-page: https://github.com/yuhangwang/plot
Author: Yuhang(Steven) Wang
License: MIT/X11
Platform: UNKNOWN
Requires-Python: >3.3
